tracenl/__main__.py
tracenl-0.1.dist-info/LICENSE
tracenl-0.1.dist-info/LICENSE~
tracenl-0.1.dist-info/METADATA
tracenl-0.1.dist-info/WHEEL
tracenl-0.1.dist-info/entry_points.txt
tracenl-0.1.dist-info/top_level.txt
tracenl-0.1.dist-info/RECORD
