Metadata-Version: 2.1
Name: tracenl
Version: 0.1
Summary: Easily snoop on netlink messages with ptrace
Home-page: http://github.com/deactivated/python-nltrace
Author: Mike Spindel
Author-email: mike@spindel.is
License: MIT
Keywords: netlink capture trace
Platform: UNKNOWN
Classifier: Development Status :: 3 - Alpha
Classifier: License :: OSI Approved :: MIT License
Classifier: Intended Audience :: Developers
Classifier: Natural Language :: English
Classifier: Programming Language :: Python :: 3
Classifier: Operating System :: POSIX :: Linux
Requires-Python: >=3.6
Requires-Dist: pyroute2
Requires-Dist: python-ptrace
